CPPinator/__init__.py
CPPinator/src/CPPinator.py
CPPinator/src/__init__.py
CPPinator/test/__init__.py
CPPinator/test/test_CPPinator.py
CPPinator-1.0.4.dist-info/LICENSE.txt
CPPinator-1.0.4.dist-info/METADATA
CPPinator-1.0.4.dist-info/WHEEL
CPPinator-1.0.4.dist-info/top_level.txt
CPPinator-1.0.4.dist-info/RECORD
