Metadata-Version: 2.1
Name: CPPinator
Version: 1.0.4
Summary: CPPinator is a Python automation script designed for compiling and running multiple C++ files in a specified directory. It simplifies the process of handling multiple C++ programs and provides a clear and organized output for each program's execution along with the execution time for each program.
Home-page: https://github.com/Hardvan/CPPinator
Author: Hardik Pawar
Author-email: hardikpawarh@gmail.com
License: UNKNOWN
Keywords: C++,automation,script,compile,run,multiple,programs,CPPinator
Platform: UNKNOWN
Classifier: Programming Language :: Python :: 3
Classifier: License :: OSI Approved :: MIT License
Classifier: Operating System :: OS Independent
Requires-Python: >=3.6
License-File: LICENSE.txt
